clockwork_tools/__init__.py
clockwork_tools/client.py
clockwork_tools-0.1.0.dist-info/WHEEL
clockwork_tools-0.1.0.dist-info/METADATA
clockwork_tools-0.1.0.dist-info/RECORD
