Metadata-Version: 2.1
Name: clockwork-tools
Version: 0.1.0
Summary: Tools to interact with Clockwork cluster
License: MIT
Author: Mila team
Requires-Python: >=3.9,<4.0
Classifier: License :: OSI Approved :: MIT License
Classifier: Programming Language :: Python :: 3
Classifier: Programming Language :: Python :: 3.10
Classifier: Programming Language :: Python :: 3.9
Requires-Dist: requests (>=2.27.1,<3.0.0)
